quantagen/__init__.py
quantagen/core.py
quantagen/image_processing.py
quantagen/utils.py
Quantagen-0.1.0.dist-info/METADATA
Quantagen-0.1.0.dist-info/WHEEL
Quantagen-0.1.0.dist-info/top_level.txt
Quantagen-0.1.0.dist-info/RECORD
