Metadata-Version: 2.1
Name: Quantagen
Version: 0.1.0
Summary: A tool for Countagen users
Home-page: https://github.com/christoffermattssonlangseth/quantagen
Author: Christoffer Mattsson Langseth
Author-email: christoffer@spatial.ist
License: LICENSE
Classifier: Development Status :: 3 - Alpha
Classifier: Intended Audience :: Science/Research
Classifier: Topic :: Scientific/Engineering :: Bio-Informatics
Classifier: License :: OSI Approved :: MIT License
Classifier: Programming Language :: Python :: 3
Classifier: Programming Language :: Python :: 3.6
Classifier: Programming Language :: Python :: 3.7
Classifier: Programming Language :: Python :: 3.8
Requires-Python: >=3.6
Requires-Dist: numpy
Requires-Dist: pandas
Requires-Dist: tifffile
Requires-Dist: scikit-image
Requires-Dist: matplotlib
